dashscope_realtime/__init__.py
dashscope_realtime/asr.py
dashscope_realtime/client.py
dashscope_realtime/config.py
dashscope_realtime/event.py
dashscope_realtime/tts.py
dashscope_realtime/__pycache__/__init__.cpython-312.pyc
dashscope_realtime/__pycache__/asr.cpython-312.pyc
dashscope_realtime/__pycache__/client.cpython-312.pyc
dashscope_realtime/__pycache__/event.cpython-312.pyc
dashscope_realtime/__pycache__/tts.cpython-312.pyc
dashscope_realtime-0.1.8.dist-info/licenses/LICENSE
dashscope_realtime-0.1.8.dist-info/METADATA
dashscope_realtime-0.1.8.dist-info/WHEEL
dashscope_realtime-0.1.8.dist-info/top_level.txt
dashscope_realtime-0.1.8.dist-info/RECORD
