Metadata-Version: 2.4
Name: dashscope-realtime
Version: 0.1.8
Summary: DashScope Realtime ASR & TTS SDK
Home-page: https://github.com/mikuh/dashscope-realtime
Author: mikuh
Author-email: geb <853934146@qq.com>
License: MIT License
Project-URL: Homepage, https://github.com/mikuh/dashscope-realtime
Requires-Python: >=3.8
License-File: LICENSE
Requires-Dist: websockets>=12.0
Dynamic: license-file
